zeleva/__init__.py
zeleva/main.py
zeleva-0.0.1.dist-info/METADATA
zeleva-0.0.1.dist-info/WHEEL
zeleva-0.0.1.dist-info/top_level.txt
zeleva-0.0.1.dist-info/RECORD
